{
  "registries": [
    {
      "kind": "git",
      "repository": "https://github.com/azure-sdk/vcpkg-betas",
      "baseline": "e226eb5b0e30055c82dcf2d0ed7b48d82ea04e5f",
      "packages": [
        "azure-core-cpp",
        "azure-identity-cpp",
        "azure-security-keyvault-common-cpp",
        "azure-security-keyvault-keys-cpp",
        "azure-storage-blobs-cpp",
        "azure-storage-common-cpp",
        "azure-storage-files-datalake-cpp",
        "azure-storage-files-shares-cpp"
      ]
    }
  ]
}